datalogger/__init__.py
datalogger/abstract_instrument.py
datalogger/version.py
datalogger/instruments/AG34461A.py
datalogger/instruments/AG34461A_4W.py
datalogger/instruments/AG34461A_avg.py
datalogger/instruments/AG34972A.py
datalogger/instruments/AG53230A.py
datalogger/instruments/FPC1000.py
datalogger/instruments/FSV30.py
datalogger/instruments/HP53132A.py
datalogger/instruments/LS350.py
datalogger/instruments/NRP2.py
datalogger/instruments/PM100D.py
datalogger/instruments/Sym5125A.py
datalogger/instruments/T7Pro.py
datalogger/instruments/TPG261.py
datalogger/instruments/__init__.py
datalogger/instruments/testDevice.py
datalogger_tf-0.2.1.data/scripts/datalogger-gui
datalogger_tf-0.2.1.dist-info/licenses/LICENSE
datalogger_tf-0.2.1.dist-info/METADATA
datalogger_tf-0.2.1.dist-info/WHEEL
datalogger_tf-0.2.1.dist-info/top_level.txt
datalogger_tf-0.2.1.dist-info/RECORD
