Metadata-Version: 2.4
Name: datalogger-tf
Version: 0.2.1
Summary: datalogger-tf is a GUI interfaced software to log multiple instruments via ethernet, usb or serial connection.
Home-page: https://gitlab.com/pythonbase1/datalogger
Author: Baptiste Marechal
Maintainer: Benoit Dubois
Maintainer-email: benoit.dubois@femto-engineering.fr
License: GPL-3.0-or-later
Classifier: Development Status :: 4 - Beta
Classifier: Environment :: X11 Applications :: Qt
Classifier: Intended Audience :: End Users/Desktop
Classifier: Natural Language :: English
Classifier: Operating System :: POSIX
Classifier: Programming Language :: Python
Classifier: Topic :: Scientific/Engineering
License-File: LICENSE
Requires-Dist: PyQt6
Requires-Dist: numpy
Requires-Dist: telnetlib3
Requires-Dist: pyserial
Requires-Dist: labjack-ljm
Dynamic: author
Dynamic: classifier
Dynamic: home-page
Dynamic: license
Dynamic: license-file
Dynamic: maintainer
Dynamic: maintainer-email
Dynamic: requires-dist
Dynamic: summary
